{
  "type": "object",
  "properties": {
    "category": {
      "type": "string",
      "enum": [
        "fraud",
        "card",
        "transfer",
        "service",
        "other"
      ]
    },
    "severity": {
      "type": "string",
      "enum": [
        "low",
        "medium",
        "high"
      ]
    },
    "summary": {
      "type": "string"
    },
    "actions": {
      "type": "array",
      "items": {
        "type": "string"
      }
    }
  },
  "required": [
    "category",
    "severity",
    "summary"
  ],
  "additionalProperties": false
}